{"data_mtime": 1636528220, "dep_lines": [1, 2, 3, 5, 6, 1, 1, 1, 1, 1, 1, 1, 1, 1, 1, 1, 1, 1], "dep_prios": [10, 5, 5, 5, 5, 5, 30, 30, 30, 30, 30, 30, 30, 30, 30, 30, 30, 30], "dependencies": ["os", "flask", "twitapp2.models", "twitapp2.twitter", "twitapp2.predict", "builtins", "abc", "flask.app", "flask.globals", "flask.scaffold", "flask.templating", "flask.wrappers", "typing", "werkzeug", "werkzeug.sansio", "werkzeug.sansio.request", "werkzeug.wrappers", "werkzeug.wrappers.request"], "hash": "2544237bea0d4c5dc8fa7c27a442d5d8ac90fd69bf92dbf63cda7419f0d3a020", "id": "twitapp2.app", "ignore_all": false, "interface_hash": "400b8603e758d50c57a7b9fa100b1de171ae2814f3fccefe0966e5f7f3614cdc", "mtime": 1636533115, "options": {"allow_redefinition": false, "allow_untyped_globals": false, "always_false": [], "always_true": [], "bazel": false, "check_untyped_defs": false, "disallow_any_decorated": false, "disallow_any_explicit": false, "disallow_any_expr": false, "disallow_any_generics": false, "disallow_any_unimported": false, "disallow_incomplete_defs": false, "disallow_subclassing_any": false, "disallow_untyped_calls": false, "disallow_untyped_decorators": false, "disallow_untyped_defs": false, "follow_imports": "silent", "follow_imports_for_stubs": false, "ignore_errors": false, "ignore_missing_imports": true, "implicit_reexport": true, "local_partial_types": false, "mypyc": false, "no_implicit_optional": false, "platform": "darwin", "plugins": [], "show_none_errors": true, "strict_equality": false, "strict_optional": true, "strict_optional_whitelist": null, "warn_no_return": true, "warn_return_any": false, "warn_unreachable": false, "warn_unused_ignores": false}, "path": "/Users/chunyanwang/Christine_documents/Data_Science/LambdaSchool/DS-Unit-3-Sprint-3-Productization-and-Cloud-master/apps/twitapp2/twitapp2/app.py", "plugin_data": null, "size": 2631, "suppressed": [], "version_id": "0.910"}